eq_finances/__init__.py
eq_finances/eq_finances.py
eq_finances-0.1.3.dist-info/LICENSE.txt
eq_finances-0.1.3.dist-info/METADATA
eq_finances-0.1.3.dist-info/WHEEL
eq_finances-0.1.3.dist-info/top_level.txt
eq_finances-0.1.3.dist-info/RECORD
