Metadata-Version: 2.1
Name: eq-finances
Version: 0.1.3
Summary: Uma biblioteca feita com várias funcionalidades, cálculos financeiros básicos e análises financeiras
Home-page: https://github.com/AnnyelCordeiro/EQFINANCE
Author: Annyel Cordeiro da Silva
Author-email: annyel.cds0202@gmail.com
Maintainer: Antonio Igor Moreira Paixao
Maintainer-email: igorm5279@gmail.com
Classifier: Programming Language :: Python :: 3
Classifier: License :: OSI Approved :: MIT License
Classifier: Operating System :: OS Independent
Requires-Python: >=3.6
License-File: LICENSE.txt
Requires-Dist: numpy
Requires-Dist: pandas
Requires-Dist: matplotlib
Requires-Dist: yfinance
Requires-Dist: requests
